unibuf/__init__.py
unibuf/_unibuf.c
unibuf/_unibuf.pyi
unibuf/_unibuf.c
unibuf/_unibuf.cp38-win_amd64.pyd
unibuf/_unibuf.pyi
unibuf/__init__.py
unibuf-0.1.1.dist-info/WHEEL
unibuf-0.1.1.dist-info/METADATA
unibuf-0.1.1.dist-info/RECORD
